{
    "appinfo": {
        "name": "Full-featured Demo",
        "version": "V1.0",
        "description": "A full-featured demo with all types of input widgets, as well as to demonstrate different running modes",
        "slogan":"",
        "developer": "",
        "contact": "",
        "homepage": "",
        "license": "",
        "standard": ""
    },
    "gcipars": {
        "cuiapp": "demo.py",
        "checkcui":"True",
        "interpreter":"python",
        "miniui":"True",
        "atqctrl": "True",
        "cmdctrl": "True",
        "icon": "icon.ico",
        "logo": "logo.png",
        "splash": "splash.png",
        "help": "",
        "wait": "wait.gif",
        "fadeio":"True",
        "transparency":"240",
        "sptime": "5",
        "spmaxsz": "[480,240]",
        "fontsz": "12",
        "logomaxsz": "[240,120]",
        "parasz": "[640,320]",
        "infowidth": "400",
        "descsz": "[380,60]",
        "titwrap": "180",
        "hpwrap": "240",
        "cmdsz": "[640,64]",
        "waitsz": "[480,96]"
    },
    "cuipars": {
        "si_1": {
            "title": "Short string",
            "type": "string",
            "style": "single",
            "label": "pos1",
            "requirement": "True",
            "exclusive": "False",
            "limitation": "min6",
            "default": "",
            "help": "short string, the basic text for most other data types"
        },
        "si_2": {
            "title": "Multiple strings",
            "type": "string",
            "style": "multiple",
            "label": "-b",
            "requirement": "False",
            "exclusive": "False",
            "limitation": "",
            "default": "",
            "help": "multiple strings"
        },
        "si_3": {
            "title": "Password",
            "type": "string",
            "style": "password",
            "label": "-p",
            "requirement": "False",
            "exclusive": "False",
            "limitation": "min6",
            "default": "123456",
            "help": "password, masked text for input"
        },
        "si_4": {
            "title": "Int",
            "type": "int",
            "style": "",
            "label": "pos2",
            "requirement": "True",
            "exclusive": "False",
            "limitation": "[0,100]",
            "default": "50",
            "help": "int value, supports minus"
        },
        "si_5": {
            "title": "Float",
            "type": "float",
            "style": "",
            "label": "pos3",
            "requirement": "True",
            "exclusive": "False",
            "limitation": "(-1,1)",
            "default": "-0.5",
            "help": "float value, supports minus"
        },
        "si_6": {
            "title": "Single file",
            "type": "file",
            "style": "single",
            "label": "-f",
            "requirement": "False",
            "exclusive": "False",
            "limitation": "CFG file (*.cfg)|*.cfg|Text file (*.txt)|*.txt|All files (*.*)|*.*",
            "default": "",
            "help": "single file, please use full path"
        },
        "si_7": {
            "title": "Multiple files",
            "type": "file",
            "style": "multiple",
            "label": "--files",
            "requirement": "False",
            "exclusive": "False",
            "limitation": "Text file (*.txt)|*.txt|All files (*.*)|*.*",
            "default": "logo.gif|cui.par",
            "help": "multiple files"
        },
        "si_8": {
            "title": "Folder",
            "type": "folder",
            "style": "single",
            "label": "-e",
            "requirement": "False",
            "exclusive": "False",
            "limitation": "",
            "default": "",
            "help": "single folder"
        },
        "si_9": {
            "title": "Folders",
            "type": "folder",
            "style": "multiple",
            "label": "--dirs",
            "requirement": "False",
            "exclusive": "False",
            "limitation": "",
            "default": "",
            "help": "folders"
        },
        "si_10": {
            "title": "Single select",
            "type": "select",
            "style": "single",
            "label": "-g",
            "requirement": "False",
            "exclusive": "True",
            "limitation": "DNA|RNA|AAS",
            "default": "DNA",
            "help": "single selection"
        },
        "si_11": {
            "title": "Multiple select",
            "type": "select",
            "style": "multiple",
            "label": "-h",
            "requirement": "False",
            "exclusive": "True",
            "limitation": "DNA|RNA|AAS",
            "default": "",
            "help": "multiple selections"
        },
        "si_12": {
            "title": "Check",
            "type": "check",
            "style": "",
            "label": "-x",
            "requirement": "False",
            "exclusive": "False",
            "limitation": "",
            "default": "true",
            "help": "check option"
        },
        "si_13": {
            "title": "Range",
            "type": "range",
            "style": "",
            "label": "--rg",
            "requirement": "True",
            "exclusive": "False",
            "limitation": "",
            "default": "(0,100]",
            "help": "range value (numerical interval)"
        },
        "si_14": {
            "title": "Colour",
            "type": "colour",
            "style": "single",
            "label": "-c",
            "requirement": "False",
            "exclusive": "False",
            "limitation": "",
            "default": "#D03429",
            "help": "colour (hex color codes)"
        },
        "si_15": {
            "title": "Colour",
            "type": "colour",
            "style": "multiple",
            "label": "--cs",
            "requirement": "False",
            "exclusive": "False",
            "limitation": "",
            "default": "#D03429",
            "help": "colour list"
        }
    }
}